examples/Request_create_EE.py
examples/Request_create_OV_ssl.py
examples/Request_schedule_call.py
examples/__init__.py
examples/get_request.py
xolphin/__init__.py
xolphin/client.py
xolphin/certificate_requests/__init__.py
xolphin/certificate_requests/configure_validation_call.py
xolphin/certificate_requests/create_certificate_request.py
xolphin/certificate_requests/create_ee_request.py
xolphin/certificate_requests/reissue_certificate_request.py
xolphin/certificate_requests/renew_certificate_request.py
xolphin/endpoint/__init__.py
xolphin/endpoint/certificate.py
xolphin/endpoint/request.py
xolphin/endpoint/support.py
xolphin/responses/__init__.py
xolphin/responses/base.py
xolphin/responses/certificate.py
xolphin/responses/certificates.py
xolphin/responses/csr.py
xolphin/responses/note.py
xolphin/responses/notes.py
xolphin/responses/product.py
xolphin/responses/product_price.py
xolphin/responses/products.py
xolphin/responses/request.py
xolphin/responses/request_ee.py
xolphin/responses/request_validation.py
xolphin/responses/request_validation_domain.py
xolphin/responses/requests.py
xolphin_api-1.7.0.dist-info/METADATA
xolphin_api-1.7.0.dist-info/WHEEL
xolphin_api-1.7.0.dist-info/top_level.txt
xolphin_api-1.7.0.dist-info/RECORD
