Metadata-Version: 2.1
Name: xolphin-api
Version: 1.7.0
Summary: Python library for Xolphin API
Home-page: https://github.com/xolphin/xolphin-api-python
Author: Xolphin
Author-email: info@xolphin.com
License: MIT
Keywords: xolphin
Classifier: Development Status :: 5 - Production/Stable
Classifier: Intended Audience :: Developers
Classifier: License :: OSI Approved :: Apache Software License
Classifier: Operating System :: OS Independent
Classifier: Topic :: Software Development :: Libraries :: Python Modules
Classifier: Topic :: Internet
Classifier: Programming Language :: Python
Classifier: Programming Language :: Python :: 2
Classifier: Programming Language :: Python :: 2.7
Classifier: Programming Language :: Python :: 3
Classifier: Programming Language :: Python :: 3.5
Requires-Dist: future
Requires-Dist: requests
